tensorflow_auto_detect-1.10.1.dist-info/METADATA
tensorflow_auto_detect-1.10.1.dist-info/RECORD
tensorflow_auto_detect-1.10.1.dist-info/WHEEL
tensorflow_auto_detect-1.10.1.dist-info/top_level.txt
tfdetect/__init__.py
tfdetect/cuda.py
tfdetect/pkg.py
tfdetect/test_pkg.py
tfdetect/utils.py
