Metadata-Version: 2.1
Name: tensorflow-auto-detect
Version: 1.10.1
Summary: UNKNOWN
Home-page: UNKNOWN
Author: Trevor Joynson
Author-email: github@skywww.net
License: GPL
Keywords: tensorflow,wtf
Platform: UNKNOWN
Provides-Extra: all
Provides-Extra: setup
Provides-Extra: install
Provides-Extra: lint
Provides-Extra: setup_requires
Provides-Extra: tests_require
Provides-Extra: tests
Requires-Dist: coveralls
Requires-Dist: tox
Requires-Dist: pylint2junit
Requires-Dist: pytest
Requires-Dist: coverage
Requires-Dist: pytest-cov
Requires-Dist: mock
Requires-Dist: pylint
Requires-Dist: setuptools (>=17.1)
Provides-Extra: all
Requires-Dist: coveralls; extra == 'all'
Requires-Dist: tox; extra == 'all'
Requires-Dist: pylint2junit; extra == 'all'
Requires-Dist: pytest; extra == 'all'
Requires-Dist: coverage; extra == 'all'
Requires-Dist: pytest-cov; extra == 'all'
Requires-Dist: mock; extra == 'all'
Requires-Dist: pylint; extra == 'all'
Requires-Dist: setuptools (>=17.1); extra == 'all'
Provides-Extra: install
Provides-Extra: lint
Requires-Dist: pylint2junit; extra == 'lint'
Requires-Dist: pylint; extra == 'lint'
Provides-Extra: setup
Requires-Dist: setuptools (>=17.1); extra == 'setup'
Provides-Extra: setup_requires
Requires-Dist: setuptools (>=17.1); extra == 'setup_requires'
Provides-Extra: tests
Requires-Dist: coveralls; extra == 'tests'
Requires-Dist: tox; extra == 'tests'
Requires-Dist: pytest; extra == 'tests'
Requires-Dist: coverage; extra == 'tests'
Requires-Dist: pytest-cov; extra == 'tests'
Requires-Dist: mock; extra == 'tests'
Provides-Extra: tests_require
Requires-Dist: coveralls; extra == 'tests_require'
Requires-Dist: tox; extra == 'tests_require'
Requires-Dist: pytest; extra == 'tests_require'
Requires-Dist: coverage; extra == 'tests_require'
Requires-Dist: pytest-cov; extra == 'tests_require'
Requires-Dist: mock; extra == 'tests_require'
